Eigen/Array
Eigen/CMakeLists.txt
Eigen/Cholesky
Eigen/CholmodSupport
Eigen/Core
Eigen/Dense
Eigen/Eigen
Eigen/Eigen2Support
Eigen/Eigenvalues
Eigen/Geometry
Eigen/Householder
Eigen/IterativeLinearSolvers
Eigen/Jacobi
Eigen/LU
Eigen/LeastSquares
Eigen/MetisSupport
Eigen/OrderingMethods
Eigen/PaStiXSupport
Eigen/PardisoSupport
Eigen/QR
Eigen/QtAlignedMalloc
Eigen/SPQRSupport
Eigen/SVD
Eigen/Sparse
Eigen/SparseCholesky
Eigen/SparseCore
Eigen/SparseLU
Eigen/SparseQR
Eigen/StdDeque
Eigen/StdList
Eigen/StdVector
Eigen/SuperLUSupport
Eigen/UmfPackSupport
Eigen/src/CMakeLists.txt
Eigen/src/Cholesky/CMakeLists.txt
Eigen/src/Cholesky/LDLT.h
Eigen/src/Cholesky/LLT.h
Eigen/src/Cholesky/LLT_MKL.h
Eigen/src/CholmodSupport/CMakeLists.txt
Eigen/src/CholmodSupport/CholmodSupport.h
Eigen/src/Core/Array.h
Eigen/src/Core/ArrayBase.h
Eigen/src/Core/ArrayWrapper.h
Eigen/src/Core/Assign.h
Eigen/src/Core/Assign_MKL.h
Eigen/src/Core/BandMatrix.h
Eigen/src/Core/Block.h
Eigen/src/Core/BooleanRedux.h
Eigen/src/Core/CMakeLists.txt
Eigen/src/Core/CommaInitializer.h
Eigen/src/Core/CoreIterators.h
Eigen/src/Core/CwiseBinaryOp.h
Eigen/src/Core/CwiseNullaryOp.h
Eigen/src/Core/CwiseUnaryOp.h
Eigen/src/Core/CwiseUnaryView.h
Eigen/src/Core/DenseBase.h
Eigen/src/Core/DenseCoeffsBase.h
Eigen/src/Core/DenseStorage.h
Eigen/src/Core/Diagonal.h
Eigen/src/Core/DiagonalMatrix.h
Eigen/src/Core/DiagonalProduct.h
Eigen/src/Core/Dot.h
Eigen/src/Core/EigenBase.h
Eigen/src/Core/Flagged.h
Eigen/src/Core/ForceAlignedAccess.h
Eigen/src/Core/Functors.h
Eigen/src/Core/Fuzzy.h
Eigen/src/Core/GeneralProduct.h
Eigen/src/Core/GenericPacketMath.h
Eigen/src/Core/GlobalFunctions.h
Eigen/src/Core/IO.h
Eigen/src/Core/Map.h
Eigen/src/Core/MapBase.h
Eigen/src/Core/MathFunctions.h
Eigen/src/Core/Matrix.h
Eigen/src/Core/MatrixBase.h
Eigen/src/Core/NestByValue.h
Eigen/src/Core/NoAlias.h
Eigen/src/Core/NumTraits.h
Eigen/src/Core/PermutationMatrix.h
pyzeo-0.1.7.dist-info/METADATA
pyzeo-0.1.7.dist-info/WHEEL
pyzeo-0.1.7.dist-info/top_level.txt
pyzeo-0.1.7.dist-info/RECORD
pyzeo-0.1.7.dist-info/licenses/LICENSE
